blocksync/__init__.py
blocksync/consts.py
blocksync/file.py
blocksync/interrupt.py
blocksync/syncer.py
blocksync/utils.py
blocksync-0.2.1.dist-info/LICENSE
blocksync-0.2.1.dist-info/METADATA
blocksync-0.2.1.dist-info/WHEEL
blocksync-0.2.1.dist-info/top_level.txt
blocksync-0.2.1.dist-info/RECORD
